launchcontainers/__init__.py
launchcontainers/_version.py
launchcontainers/check/__init__.py
launchcontainers/check/check_dwi_pipelines.py
launchcontainers/cli.py
launchcontainers/clusters/__init__.py
launchcontainers/clusters/dask_scheduler.py
launchcontainers/clusters/local.py
launchcontainers/clusters/sge.py
launchcontainers/clusters/slurm.py
launchcontainers/config_logger.py
launchcontainers/do_launch.py
launchcontainers/do_prepare.py
launchcontainers/example_configs/example_configs_0.4.2.zip
launchcontainers/gen_launch_cmd.py
launchcontainers/other_cli_tool/__init__.py
launchcontainers/other_cli_tool/copy_configs.py
launchcontainers/other_cli_tool/create_bids.py
launchcontainers/other_cli_tool/mrhelp.py
launchcontainers/other_cli_tool/salloc_dwi_worker.txt
launchcontainers/other_cli_tool/zip_example_config.py
launchcontainers/output_QC/01_check_dicom_and_nifti.ipynb
launchcontainers/output_QC/05_check_statsmaps.py
launchcontainers/output_QC/__init__.py
launchcontainers/output_QC/qc_rtp2pipeline_output.py
launchcontainers/output_QC/qc_rtp2preproc_output.py
launchcontainers/prepare/__init__.py
launchcontainers/prepare/dwi_prepare_input.py
launchcontainers/prepare/prepare_dwi.py
launchcontainers/prepare_MR_pipeline/00_dicom_to_nifti/QA_check_json.py
launchcontainers/prepare_MR_pipeline/00_dicom_to_nifti/createSubSesList_Dicoms.sh
launchcontainers/prepare_MR_pipeline/00_dicom_to_nifti/create_subseslist.sh
launchcontainers/prepare_MR_pipeline/00_dicom_to_nifti/example_subseslist_heudiconv.txt
launchcontainers/prepare_MR_pipeline/00_dicom_to_nifti/gen_subseslist_from_dicom_folder.py
launchcontainers/prepare_MR_pipeline/00_dicom_to_nifti/get_folder_depth.py
launchcontainers/prepare_MR_pipeline/00_dicom_to_nifti/heudiconv_analysis_note.txt
launchcontainers/prepare_MR_pipeline/00_dicom_to_nifti/heuristic/heuristic_BCBL.py
launchcontainers/prepare_MR_pipeline/00_dicom_to_nifti/heuristic/heuristic_test.py
launchcontainers-0.4.2.dist-info/LICENSE
launchcontainers-0.4.2.dist-info/METADATA
launchcontainers-0.4.2.dist-info/WHEEL
launchcontainers-0.4.2.dist-info/entry_points.txt
launchcontainers-0.4.2.dist-info/RECORD
