Metadata-Version: 2.1
Name: launchcontainers
Version: 0.4.2
Summary: A Python based soft to launch neuroimaging containers on clusters
Home-page: https://github.com/garikoitz/launchcontainers
License: MIT
Keywords: HPC,MRI,nilearn,RTP2,DWI,dMRI
Author: Garikoitz Lerma-Usabiaga
Maintainer: Garikoitz Lerma-Usabiaga
Requires-Python: >=3.10,<4.0
Classifier: License :: OSI Approved :: MIT License
Classifier: Programming Language :: Python :: 3
Classifier: Programming Language :: Python :: 3.10
Classifier: Programming Language :: Python :: 3.11
Classifier: Programming Language :: Python :: 3.10
Classifier: Programming Language :: Python :: 3.11
Classifier: Programming Language :: Python :: 3.12
Classifier: Topic :: Software Development :: Libraries :: Python Modules
Requires-Dist: PyYAML
Requires-Dist: bids
Requires-Dist: bokeh (>=2.4.2)
Requires-Dist: coverage-conditional-plugin (>=0.7.0,<0.8.0)
Requires-Dist: dask (>=2024.1.0)
Requires-Dist: dask-jobqueue (>=0.8.5)
Requires-Dist: distributed (>=2024.1.0)
Requires-Dist: heudiconv (>=1.3.2)
Requires-Dist: ipython (>=7.29.0)
Requires-Dist: nibabel
Requires-Dist: numpy
Requires-Dist: pandas
Requires-Dist: pybids (>=0.16.1,<0.17.0)
Requires-Dist: requests (>=2.26,<3.0)
Requires-Dist: scipy
Requires-Dist: setuptools (>=67.0.0,<68.0.0)
Project-URL: Repository, https://github.com/garikoitz/launchcontainers
